README.rst
setup.py
django_libretto/__init__.py
django_libretto/decorators.py
django_libretto/forms.py
django_libretto/http.py
django_libretto/models.py
django_libretto/template.py
django_libretto/url.py
django_libretto.egg-info/PKG-INFO
django_libretto.egg-info/SOURCES.txt
django_libretto.egg-info/dependency_links.txt
django_libretto.egg-info/top_level.txt
django_libretto/templatetags/__init__.py
django_libretto/templatetags/navigation.py