Metadata-Version: 1.0
Name: django-libretto
Version: 1.0.0
Summary: Collection of useful Django snippets
Home-page: https://github.com/ze-phyr-us/django-libretto
Author: Vita Smid
Author-email: me@ze.phyr.us
License: MIT
Platform: UNKNOWN
